dcss/__init__.py
dcss/main.py
dcss/main_external_demo.py
dcss/main_external_demo_fastdownward.py
dcss/main_webserver.py
dcss/main_webserver_direct_access.py
dcss/main_webserver_direct_access_threading.py
dcss/main_webserver_external_2.py
dcss/websockgame.py
dcss/actions/__init__.py
dcss/actions/action.py
dcss/actions/command.py
dcss/actions/menuchoice.py
dcss/agent/SimpleRandomAgent.py
dcss/agent/__init__.py
dcss/agent/base.py
dcss/agent/debug_agent.py
dcss/agent/fastdownwardplanningagent.py
dcss/agent/fastdownwardtutorial1.py
dcss/agent/humaninterfaceagent.py
dcss/agent/randomagent.py
dcss/agent/simplerlagent.py
dcss/agent/testallcommandsagent.py
dcss/connection/__init__.py
dcss/connection/autobahn_game_connection.py
dcss/connection/config.py
dcss/connection/game_connection.py
dcss/connection/menuknowledge.py
dcss/connection/state.py
dcss/connection/states/__init__.py
dcss/connection/states/initial.py
dcss/state/__init__.py
dcss/state/cell.py
dcss/state/cellmap.py
dcss/state/cellrawstrdatum.py
dcss/state/game-MSI.py
dcss/state/game.py
dcss/state/inventoryitem.py
dcss/state/itemproperty.py
dcss/state/menu.py
dcss/state/monster.py
dcss/state/mutation-MSI.py
dcss/state/mutation.py
dcss/state/player-MSI.py
dcss/state/player.py
dcss/state/skill.py
dcss/state/spell.py
dcss/state/statuseffect-MSI.py
dcss/state/statuseffect.py
dcss/state/tilefeatures.py
dcss_ai_wrapper_dtdannen-0.0.8.dist-info/LICENSE
dcss_ai_wrapper_dtdannen-0.0.8.dist-info/METADATA
dcss_ai_wrapper_dtdannen-0.0.8.dist-info/WHEEL
dcss_ai_wrapper_dtdannen-0.0.8.dist-info/top_level.txt
dcss_ai_wrapper_dtdannen-0.0.8.dist-info/RECORD
